SendTextSMTP/SendText.py
SendTextSMTP/__init__.py
sendtextsmtp-0.4.11.dist-info/METADATA
sendtextsmtp-0.4.11.dist-info/WHEEL
sendtextsmtp-0.4.11.dist-info/licenses/LICENSE
sendtextsmtp-0.4.11.dist-info/RECORD
