Metadata-Version: 2.3
Name: SendTextSMTP
Version: 0.4.11
Summary: A simple package to simplify the process to send text messages using the SMTP mail protocol.
Project-URL: Homepage, https://github.com/Foxtrot2400/sendtext_SMTP
Project-URL: Issues, https://github.com/Foxtrot2400/sendtext_SMTP/issues
Author-email: Foxtrot2400 <thefoxtrot2400@gmail.com>
License-File: LICENSE
Classifier: License :: OSI Approved :: MIT License
Classifier: Operating System :: OS Independent
Classifier: Programming Language :: Python :: 3
Requires-Python: >=3.6
